odoo/addons/automatic_monthly_invoicing/README.rst
odoo/addons/automatic_monthly_invoicing/__init__.py
odoo/addons/automatic_monthly_invoicing/__manifest__.py
odoo/addons/automatic_monthly_invoicing/data/cron.xml
odoo/addons/automatic_monthly_invoicing/i18n/es.po
odoo/addons/automatic_monthly_invoicing/models/__init__.py
odoo/addons/automatic_monthly_invoicing/models/res_partner.py
odoo/addons/automatic_monthly_invoicing/models/sale_order.py
odoo/addons/automatic_monthly_invoicing/static/description/icon.png
odoo/addons/automatic_monthly_invoicing/views/res_partner_views.xml
odoo/addons/automatic_monthly_invoicing/views/sale_views.xml
odoo_addon_automatic_monthly_invoicing-15.0.1.0.1.dist-info/METADATA
odoo_addon_automatic_monthly_invoicing-15.0.1.0.1.dist-info/WHEEL
odoo_addon_automatic_monthly_invoicing-15.0.1.0.1.dist-info/top_level.txt
odoo_addon_automatic_monthly_invoicing-15.0.1.0.1.dist-info/RECORD
